steamid_oidc/__init__.py
steamid_oidc/steamid_oidc.py
steamid_oidc-0.1.0.dist-info/METADATA
steamid_oidc-0.1.0.dist-info/WHEEL
steamid_oidc-0.1.0.dist-info/top_level.txt
steamid_oidc-0.1.0.dist-info/RECORD
